piwik_pro_log_analytics/__init__.py
piwik_pro_log_analytics/import_logs.py
piwik_pro_log_analytics-5.2.1.dist-info/entry_points.txt
piwik_pro_log_analytics-5.2.1.dist-info/LICENSE.txt
piwik_pro_log_analytics-5.2.1.dist-info/WHEEL
piwik_pro_log_analytics-5.2.1.dist-info/METADATA
piwik_pro_log_analytics-5.2.1.dist-info/RECORD
