Metadata-Version: 2.1
Name: piwik-pro-log-analytics
Version: 5.2.1
Summary: Allows importing common web server log formats (nginx, apache, iss and more) directly to Piwik PRO. It's Free Software available under GPLv3 license, available on GitHub
License: GPL-3.0-or-later
Author: Piwik PRO
Author-email: kosto@piwik.pro
Requires-Python: >=3.6
Classifier: License :: OSI Approved :: GNU General Public License v3 or later (GPLv3+)
Classifier: Programming Language :: Python :: 3
Classifier: Programming Language :: Python :: 3.10
Classifier: Programming Language :: Python :: 3.6
Classifier: Programming Language :: Python :: 3.7
Classifier: Programming Language :: Python :: 3.8
Classifier: Programming Language :: Python :: 3.9
